<annotation>
	<folder>c</folder>
	<filename>2401.jpg</filename>
	<path>D:\allwater\c\2401.jpg</path>
	<source>
		<database>Unknown</database>
	</source>
	<size>
		<width>800</width>
		<height>800</height>
		<depth>3</depth>
	</size>
	<segmented>0</segmented>
	<object>
		<name>0</name>
		<pose>Unspecified</pose>
		<truncated>0</truncated>
		<difficult>0</difficult>
		<bndbox>
			<xmin>148</xmin>
			<ymin>232</ymin>
			<xmax>217</xmax>
			<ymax>325</ymax>
		</bndbox>
	</object>
	<object>
		<name>2</name>
		<pose>Unspecified</pose>
		<truncated>0</truncated>
		<difficult>0</difficult>
		<bndbox>
			<xmin>249</xmin>
			<ymin>236</ymin>
			<xmax>316</xmax>
			<ymax>330</ymax>
		</bndbox>
	</object>
	<object>
		<name>3</name>
		<pose>Unspecified</pose>
		<truncated>0</truncated>
		<difficult>0</difficult>
		<bndbox>
			<xmin>346</xmin>
			<ymin>235</ymin>
			<xmax>415</xmax>
			<ymax>331</ymax>
		</bndbox>
	</object>
	<object>
		<name>2</name>
		<pose>Unspecified</pose>
		<truncated>0</truncated>
		<difficult>0</difficult>
		<bndbox>
			<xmin>437</xmin>
			<ymin>236</ymin>
			<xmax>508</xmax>
			<ymax>330</ymax>
		</bndbox>
	</object>
	<object>
		<name>7</name>
		<pose>Unspecified</pose>
		<truncated>0</truncated>
		<difficult>0</difficult>
		<bndbox>
			<xmin>530</xmin>
			<ymin>198</ymin>
			<xmax>598</xmax>
			<ymax>290</ymax>
		</bndbox>
	</object>
	<object>
		<name>8</name>
		<pose>Unspecified</pose>
		<truncated>0</truncated>
		<difficult>0</difficult>
		<bndbox>
			<xmin>535</xmin>
			<ymin>300</ymin>
			<xmax>600</xmax>
			<ymax>382</ymax>
		</bndbox>
	</object>
</annotation>
