<annotation>
	<folder>WaterMeter</folder>
	<filename>660.jpg</filename>
	<path>E:\Technology\ML\LabelTool\DataSet\WaterMeter\660.jpg</path>
	<source>
		<database>Unknown</database>
	</source>
	<size>
		<width>800</width>
		<height>800</height>
		<depth>3</depth>
	</size>
	<segmented>0</segmented>
	<object>
		<name>0</name>
		<pose>Unspecified</pose>
		<truncated>0</truncated>
		<difficult>0</difficult>
		<bndbox>
			<xmin>333</xmin>
			<ymin>198</ymin>
			<xmax>381</xmax>
			<ymax>265</ymax>
		</bndbox>
	</object>
	<object>
		<name>0</name>
		<pose>Unspecified</pose>
		<truncated>0</truncated>
		<difficult>0</difficult>
		<bndbox>
			<xmin>399</xmin>
			<ymin>194</ymin>
			<xmax>449</xmax>
			<ymax>263</ymax>
		</bndbox>
	</object>
	<object>
		<name>3</name>
		<pose>Unspecified</pose>
		<truncated>0</truncated>
		<difficult>0</difficult>
		<bndbox>
			<xmin>472</xmin>
			<ymin>197</ymin>
			<xmax>523</xmax>
			<ymax>266</ymax>
		</bndbox>
	</object>
	<object>
		<name>4</name>
		<pose>Unspecified</pose>
		<truncated>0</truncated>
		<difficult>0</difficult>
		<bndbox>
			<xmin>546</xmin>
			<ymin>201</ymin>
			<xmax>601</xmax>
			<ymax>273</ymax>
		</bndbox>
	</object>
	<object>
		<name>4</name>
		<pose>Unspecified</pose>
		<truncated>0</truncated>
		<difficult>0</difficult>
		<bndbox>
			<xmin>624</xmin>
			<ymin>198</ymin>
			<xmax>685</xmax>
			<ymax>279</ymax>
		</bndbox>
	</object>
</annotation>
